Metadata-Version: 1.1
Name: open-firefox-urls-chrome
Version: 0.1.2
Summary: Utility to get URLs currently open in Firefox and open them in Chrome
Home-page: https://github.com/robmcelhinney/open-firefox-urls-chrome
Author: Robert McElhinney
Author-email: robmcelhinney@hotmail.com
License: MIT
Download-URL: https://github.com/robmcelhinney/open-firefox-urls-chrome/archive/0.1.2.tar.gz
Keywords: firefox chrome util commandline
Platform: UNKNOWN
Classifier: License :: OSI Approved :: MIT License
Classifier: Programming Language :: Python :: 3.7
